yacluster.py
yacluster-1.0.0.dist-info/DESCRIPTION.rst
yacluster-1.0.0.dist-info/METADATA
yacluster-1.0.0.dist-info/RECORD
yacluster-1.0.0.dist-info/WHEEL
yacluster-1.0.0.dist-info/metadata.json
yacluster-1.0.0.dist-info/top_level.txt
